{
  "stage": "plan_execute",
  "run_id": "20260507T104805Z-2fa851d5",
  "governance_scope": "root",
  "mode": "interactive_governed",
  "internal_grade": "XL",
  "scheduler_kind": "bounded_local_xl_executor",
  "profile_id": "repo_safe_execution_closure",
  "requirement_doc_path": "E:\\Code\\repo\\ai-teaching-assistant-frontend\\docs\\requirements\\2026-05-07-local-rabbitmq-installation-on-windows-without-docker-deliverabl.md",
  "execution_plan_path": "E:\\Code\\repo\\ai-teaching-assistant-frontend\\docs\\plans\\2026-05-07-local-rabbitmq-installation-on-windows-without-docker-deliverabl-execution-plan.md",
  "execution_topology_path": "E:\\Code\\repo\\ai-teaching-assistant-frontend\\outputs\\runtime\\vibe-sessions\\20260507T104805Z-2fa851d5\\execution-topology.json",
  "runtime_input_packet_path": "E:\\Code\\repo\\ai-teaching-assistant-frontend\\outputs\\runtime\\vibe-sessions\\20260507T104805Z-2fa851d5\\runtime-input-packet.json",
  "skill_usage": {
    "schema_version": 2,
    "state_model": "binary_used_unused",
    "used": [
      {
        "skill_id": "tdd-guide",
        "skill_md_path": "C:\\Users\\Administrator\\.codeium\\windsurf-next\\skills\\vibe\\bundled\\skills\\tdd-guide\\SKILL.runtime-mirror.md",
        "skill_md_sha256": "4e23eb7fbc3fb32077d74f48c41c7b389dbe408ecf3da4971ca0ca0c8ca622c2",
        "evidence": [
          {
            "stage": "plan_execute",
            "artifact_path": "execution-manifest.json",
            "impact": "Execution manifest preserves binary skill usage truth for tdd-guide; execution cannot use routing, hints, consultation, or dispatch alone as usage proof."
          }
        ]
      }
    ],
    "unused": [
      {
        "skill_id": "verification-before-completion",
        "reason": "selected_but_no_artifact_impact"
      }
    ],
    "used_skills": [
      "tdd-guide"
    ],
    "unused_skills": [
      "verification-before-completion"
    ],
    "loaded_skills": [
      {
        "skill_id": "verification-before-completion",
        "skill_md_path": "C:\\Users\\Administrator\\.codeium\\windsurf-next\\skills\\vibe\\bundled\\skills\\verification-before-completion\\SKILL.runtime-mirror.md",
        "skill_md_sha256": "747860a51c07b4691e5ac36ccddec8e1ddd4c1940037ae56f4161eab5dfb8ce4",
        "load_status": "loaded_full_skill_md",
        "loaded_at_stage": "skeleton_check",
        "loaded_byte_count": 4535,
        "loaded_line_count": 143
      },
      {
        "skill_id": "tdd-guide",
        "skill_md_path": "C:\\Users\\Administrator\\.codeium\\windsurf-next\\skills\\vibe\\bundled\\skills\\tdd-guide\\SKILL.runtime-mirror.md",
        "skill_md_sha256": "4e23eb7fbc3fb32077d74f48c41c7b389dbe408ecf3da4971ca0ca0c8ca622c2",
        "load_status": "loaded_full_skill_md",
        "loaded_at_stage": "skeleton_check",
        "loaded_byte_count": 1820,
        "loaded_line_count": 61
      }
    ],
    "evidence": [
      {
        "skill_id": "tdd-guide",
        "stage": "requirement_doc",
        "artifact_ref": "2026-05-07-local-rabbitmq-installation-on-windows-without-docker-deliverabl.md",
        "impact_summary": "Requirement doc adopts the loaded tdd-guide SKILL.md as the workflow authority for downstream planning and completion evidence.",
        "skill_md_path": "C:\\Users\\Administrator\\.codeium\\windsurf-next\\skills\\vibe\\bundled\\skills\\tdd-guide\\SKILL.runtime-mirror.md",
        "skill_md_sha256": "4e23eb7fbc3fb32077d74f48c41c7b389dbe408ecf3da4971ca0ca0c8ca622c2"
      },
      {
        "skill_id": "tdd-guide",
        "stage": "xl_plan",
        "artifact_ref": "2026-05-07-local-rabbitmq-installation-on-windows-without-docker-deliverabl-execution-plan.md",
        "impact_summary": "Execution plan carries the loaded tdd-guide SKILL.md workflow authority into the planned verification and completion path.",
        "skill_md_path": "C:\\Users\\Administrator\\.codeium\\windsurf-next\\skills\\vibe\\bundled\\skills\\tdd-guide\\SKILL.runtime-mirror.md",
        "skill_md_sha256": "4e23eb7fbc3fb32077d74f48c41c7b389dbe408ecf3da4971ca0ca0c8ca622c2"
      },
      {
        "skill_id": "tdd-guide",
        "stage": "plan_execute",
        "artifact_ref": "execution-manifest.json",
        "impact_summary": "Execution manifest preserves binary skill usage truth for tdd-guide; execution cannot use routing, hints, consultation, or dispatch alone as usage proof.",
        "skill_md_path": "C:\\Users\\Administrator\\.codeium\\windsurf-next\\skills\\vibe\\bundled\\skills\\tdd-guide\\SKILL.runtime-mirror.md",
        "skill_md_sha256": "4e23eb7fbc3fb32077d74f48c41c7b389dbe408ecf3da4971ca0ca0c8ca622c2"
      }
    ],
    "unused_reasons": [
      {
        "skill_id": "verification-before-completion",
        "reason": "selected_but_no_artifact_impact"
      }
    ]
  },
  "skill_routing_path": "E:\\Code\\repo\\ai-teaching-assistant-frontend\\outputs\\runtime\\vibe-sessions\\20260507T104805Z-2fa851d5\\runtime-input-packet.json",
  "skill_routing_summary": {
    "candidate_count": 2,
    "selected_count": 2,
    "rejected_count": 0,
    "used_count": 1,
    "unused_count": 1
  },
  "skill_execution_lock": {
    "schema_version": "v1",
    "state": "active",
    "source": "approved_plan_reentry",
    "source_run_id": "20260507T104720Z-3bcacd5f",
    "locked_skill_ids": [
      "verification-before-completion",
      "tdd-guide",
      "scholarly-publishing"
    ],
    "locked_dispatch": [
      {
        "skill_id": "verification-before-completion",
        "skill_md_path": "C:\\Users\\Administrator\\.codeium\\windsurf-next\\skills\\vibe\\bundled\\skills\\verification-before-completion\\SKILL.runtime-mirror.md",
        "reason": "overlay recommendation from 'retrieval_advice'",
        "task_slice": "overlay recommendation from 'retrieval_advice'",
        "state": "selected",
        "dispatch_phase": "in_execution",
        "parallelizable_in_root_xl": true,
        "native_usage_required": true,
        "native_skill_entrypoint": "C:\\Users\\Administrator\\.codeium\\windsurf-next\\skills\\vibe\\bundled\\skills\\verification-before-completion\\SKILL.runtime-mirror.md",
        "skill_root": "C:\\Users\\Administrator\\.codeium\\windsurf-next\\skills\\vibe\\bundled\\skills\\verification-before-completion",
        "bounded_role": "specialist_assist",
        "must_preserve_workflow": true,
        "binding_profile": "default",
        "lane_policy": "inherit_grade",
        "write_scope": "specialist:verification-before-completion",
        "review_mode": "native_contract",
        "execution_priority": 50,
        "required_inputs": [
          "bounded specialist subtask contract",
          "frozen requirement context",
          "relevant source files or domain artifacts"
        ],
        "expected_outputs": [
          "bounded specialist findings or code changes",
          "verification notes aligned with the specialist skill"
        ],
        "verification_expectation": "Preserve the specialist skill's native workflow, boundaries, and validation style.",
        "progressive_load_policy": [
          "Open the specialist C:\\Users\\Administrator\\.codeium\\windsurf-next\\skills\\vibe\\bundled\\skills\\verification-before-completion\\SKILL.runtime-mirror.md entrypoint first.",
          "If this specialist is disclosed only by native_skill_entrypoint, keep same-session loading path-based and do not replace it with Skill(verification-before-completion) unless that skill name is explicitly host-visible in the current session."
        ],
        "legacy_source": "overlay:retrieval_advice",
        "locked_for_execution": true,
        "lock_source": "current_skill_routing_selected",
        "reconciliation_state": "current_surfaced",
        "requires_resolution": true
      },
      {
        "skill_id": "tdd-guide",
        "skill_md_path": "C:\\Users\\Administrator\\.codeium\\windsurf-next\\skills\\vibe\\bundled\\skills\\tdd-guide\\SKILL.runtime-mirror.md",
        "reason": "internal specialist recommender selected a bounded specialist candidate for governed execution",
        "task_slice": "internal specialist recommender selected a bounded specialist candidate for governed execution",
        "state": "selected",
        "dispatch_phase": "in_execution",
        "parallelizable_in_root_xl": true,
        "native_usage_required": true,
        "native_skill_entrypoint": "C:\\Users\\Administrator\\.codeium\\windsurf-next\\skills\\vibe\\bundled\\skills\\tdd-guide\\SKILL.runtime-mirror.md",
        "skill_root": "C:\\Users\\Administrator\\.codeium\\windsurf-next\\skills\\vibe\\bundled\\skills\\tdd-guide",
        "bounded_role": "specialist_assist",
        "must_preserve_workflow": true,
        "binding_profile": "default",
        "lane_policy": "inherit_grade",
        "write_scope": "specialist:tdd-guide",
        "review_mode": "native_contract",
        "execution_priority": 50,
        "required_inputs": [
          "bounded specialist subtask contract",
          "frozen requirement context",
          "relevant source files or domain artifacts"
        ],
        "expected_outputs": [
          "bounded specialist findings or code changes",
          "verification notes aligned with the specialist skill"
        ],
        "verification_expectation": "Preserve the specialist skill's native workflow, boundaries, and validation style.",
        "progressive_load_policy": [
          "Open the specialist C:\\Users\\Administrator\\.codeium\\windsurf-next\\skills\\vibe\\bundled\\skills\\tdd-guide\\SKILL.runtime-mirror.md entrypoint first.",
          "If this specialist is disclosed only by native_skill_entrypoint, keep same-session loading path-based and do not replace it with Skill(tdd-guide) unless that skill name is explicitly host-visible in the current session."
        ],
        "legacy_source": "route_selected",
        "locked_for_execution": true,
        "lock_source": "current_skill_routing_selected",
        "reconciliation_state": "current_surfaced",
        "requires_resolution": true
      },
      {
        "skill_id": "scholarly-publishing",
        "skill_md_path": "C:\\Users\\Administrator\\.codeium\\windsurf-next\\skills\\vibe\\bundled\\skills\\scholarly-publishing\\SKILL.runtime-mirror.md",
        "reason": "internal specialist recommender selected a bounded specialist candidate for governed execution",
        "task_slice": "internal specialist recommender selected a bounded specialist candidate for governed execution",
        "state": "selected",
        "dispatch_phase": "post_execution",
        "parallelizable_in_root_xl": true,
        "native_usage_required": true,
        "native_skill_entrypoint": "C:\\Users\\Administrator\\.codeium\\windsurf-next\\skills\\vibe\\bundled\\skills\\scholarly-publishing\\SKILL.runtime-mirror.md",
        "skill_root": "C:\\Users\\Administrator\\.codeium\\windsurf-next\\skills\\vibe\\bundled\\skills\\scholarly-publishing",
        "bounded_role": "specialist_assist",
        "must_preserve_workflow": true,
        "binding_profile": "deliverable",
        "lane_policy": "bounded_parallel",
        "write_scope": "specialist:deliverable:scholarly-publishing",
        "review_mode": "checkpoint_after_step",
        "execution_priority": 70,
        "required_inputs": [
          "bounded specialist subtask contract",
          "frozen requirement context",
          "relevant source files or domain artifacts"
        ],
        "expected_outputs": [
          "bounded specialist findings or code changes",
          "verification notes aligned with the specialist skill"
        ],
        "verification_expectation": "Preserve the specialist skill's native workflow, boundaries, and validation style.",
        "progressive_load_policy": [
          "Open the specialist C:\\Users\\Administrator\\.codeium\\windsurf-next\\skills\\vibe\\bundled\\skills\\scholarly-publishing\\SKILL.runtime-mirror.md entrypoint first.",
          "If this specialist is disclosed only by native_skill_entrypoint, keep same-session loading path-based and do not replace it with Skill(scholarly-publishing) unless that skill name is explicitly host-visible in the current session."
        ],
        "legacy_source": "route_selected",
        "locked_for_execution": true,
        "lock_source": "previous_skill_execution_lock",
        "reconciliation_state": "inherited_not_currently_surfaced",
        "requires_resolution": true
      }
    ],
    "resolution_required": true,
    "resolution_states": [
      "executed",
      "not_applicable",
      "deferred",
      "failed"
    ]
  },
  "specialist_lock_resolution": {
    "active": true,
    "locked_skill_ids": [
      "verification-before-completion",
      "tdd-guide",
      "scholarly-publishing"
    ],
    "executed_skill_ids": [
      "tdd-guide",
      "verification-before-completion",
      "scholarly-publishing"
    ],
    "not_applicable_skill_ids": [],
    "deferred_skill_ids": [],
    "failed_skill_ids": [],
    "unresolved_skill_ids": [],
    "delivery_blocking": false
  },
  "selected_skill_ids": [
    "verification-before-completion",
    "tdd-guide"
  ],
  "execution_memory_context_path": "E:\\Code\\repo\\ai-teaching-assistant-frontend\\outputs\\runtime\\vibe-sessions\\20260507T104805Z-2fa851d5\\memory-activation\\execution-context-pack.json",
  "generated_at": "2026-05-07T10:48:13Z",
  "planned_wave_count": 1,
  "planned_unit_count": 5,
  "executed_unit_count": 5,
  "successful_unit_count": 4,
  "failed_unit_count": 1,
  "timed_out_unit_count": 0,
  "proof_class": "runtime",
  "promotion_suitable": "bounded",
  "hierarchy": {
    "governance_scope": "root",
    "root_run_id": "20260507T104805Z-2fa851d5",
    "parent_run_id": null,
    "parent_unit_id": null,
    "inherited_requirement_doc_path": null,
    "inherited_execution_plan_path": null,
    "delegation_envelope_path": null
  },
  "authority": {
    "canonical_requirement_write_allowed": true,
    "canonical_plan_write_allowed": true,
    "global_dispatch_allowed": true,
    "completion_claim_allowed": true
  },
  "route_runtime_alignment": {
    "router_selected_skill": "tdd-guide",
    "runtime_selected_skill": "vibe",
    "skill_mismatch": true,
    "confirm_required": false,
    "requested_host_adapter_id": "windsurf",
    "effective_host_adapter_id": "windsurf"
  },
  "execution_topology": {
    "path": "E:\\Code\\repo\\ai-teaching-assistant-frontend\\outputs\\runtime\\vibe-sessions\\20260507T104805Z-2fa851d5\\execution-topology.json",
    "delegation_mode": "selective_parallel_child_lanes",
    "wave_execution": "sequential",
    "step_execution": "sequential",
    "unit_execution": "mixed",
    "max_parallel_units": 2,
    "child_lane_unit_count": 5,
    "parallelizable_specialist_unit_count": 3,
    "parallel_candidate_unit_count": 5,
    "parallel_units_executed_count": 4,
    "parallel_executed_unit_ids": [
      "runtime-neutral-freshness-gate-tests",
      "release-install-runtime-coherence-gate",
      "specialist-in_execution-ungrouped-tdd-guide-specialist",
      "specialist-in_execution-ungrouped-verification-before-completion-specialist"
    ],
    "parallel_execution_windows": [
      {
        "wave_id": "wave-1",
        "step_id": "wave-1-parallel",
        "unit_ids": [
          "runtime-neutral-freshness-gate-tests",
          "release-install-runtime-coherence-gate"
        ]
      },
      {
        "wave_id": "wave-1",
        "step_id": "wave-1-specialist-in_execution-group-1-parallel",
        "unit_ids": [
          "specialist-in_execution-ungrouped-tdd-guide-specialist",
          "specialist-in_execution-ungrouped-verification-before-completion-specialist"
        ]
      }
    ],
    "serial_execution_order": [
      "specialist-post_execution-ungrouped-scholarly-publishing-specialist"
    ],
    "review_mode": "checkpoint_per_step",
    "specialist_phase_bindings": {
      "pre_execution": [],
      "in_execution": [
        {
          "skill_id": "verification-before-completion",
          "phase_id": null,
          "reason": "overlay recommendation from 'retrieval_advice'",
          "task_slice": "overlay recommendation from 'retrieval_advice'",
          "native_skill_entrypoint": "C:\\Users\\Administrator\\.codeium\\windsurf-next\\skills\\vibe\\bundled\\skills\\verification-before-completion\\SKILL.runtime-mirror.md",
          "skill_md_path": "C:\\Users\\Administrator\\.codeium\\windsurf-next\\skills\\vibe\\bundled\\skills\\verification-before-completion\\SKILL.runtime-mirror.md",
          "dispatch_phase": "in_execution",
          "parallelizable_in_root_xl": true,
          "native_usage_required": true,
          "usage_required": true,
          "skill_root": "C:\\Users\\Administrator\\.codeium\\windsurf-next\\skills\\vibe\\bundled\\skills\\verification-before-completion",
          "bounded_role": "specialist_assist",
          "must_preserve_workflow": true,
          "binding_profile": "default",
          "lane_policy": "inherit_grade",
          "write_scope": "specialist:verification-before-completion",
          "review_mode": "native_contract",
          "execution_priority": 50,
          "required_inputs": [
            "bounded specialist subtask contract",
            "frozen requirement context",
            "relevant source files or domain artifacts"
          ],
          "expected_outputs": [
            "bounded specialist findings or code changes",
            "verification notes aligned with the specialist skill"
          ],
          "verification_expectation": "Preserve the specialist skill's native workflow, boundaries, and validation style.",
          "progressive_load_policy": [
            "Open the specialist C:\\Users\\Administrator\\.codeium\\windsurf-next\\skills\\vibe\\bundled\\skills\\verification-before-completion\\SKILL.runtime-mirror.md entrypoint first.",
            "If this specialist is disclosed only by native_skill_entrypoint, keep same-session loading path-based and do not replace it with Skill(verification-before-completion) unless that skill name is explicitly host-visible in the current session."
          ],
          "locked_for_execution": true,
          "lock_source": "current_skill_routing_selected",
          "reconciliation_state": "current_surfaced",
          "requires_resolution": true
        },
        {
          "skill_id": "tdd-guide",
          "phase_id": null,
          "reason": "internal specialist recommender selected a bounded specialist candidate for governed execution",
          "task_slice": "internal specialist recommender selected a bounded specialist candidate for governed execution",
          "native_skill_entrypoint": "C:\\Users\\Administrator\\.codeium\\windsurf-next\\skills\\vibe\\bundled\\skills\\tdd-guide\\SKILL.runtime-mirror.md",
          "skill_md_path": "C:\\Users\\Administrator\\.codeium\\windsurf-next\\skills\\vibe\\bundled\\skills\\tdd-guide\\SKILL.runtime-mirror.md",
          "dispatch_phase": "in_execution",
          "parallelizable_in_root_xl": true,
          "native_usage_required": true,
          "usage_required": true,
          "skill_root": "C:\\Users\\Administrator\\.codeium\\windsurf-next\\skills\\vibe\\bundled\\skills\\tdd-guide",
          "bounded_role": "specialist_assist",
          "must_preserve_workflow": true,
          "binding_profile": "default",
          "lane_policy": "inherit_grade",
          "write_scope": "specialist:tdd-guide",
          "review_mode": "native_contract",
          "execution_priority": 50,
          "required_inputs": [
            "bounded specialist subtask contract",
            "frozen requirement context",
            "relevant source files or domain artifacts"
          ],
          "expected_outputs": [
            "bounded specialist findings or code changes",
            "verification notes aligned with the specialist skill"
          ],
          "verification_expectation": "Preserve the specialist skill's native workflow, boundaries, and validation style.",
          "progressive_load_policy": [
            "Open the specialist C:\\Users\\Administrator\\.codeium\\windsurf-next\\skills\\vibe\\bundled\\skills\\tdd-guide\\SKILL.runtime-mirror.md entrypoint first.",
            "If this specialist is disclosed only by native_skill_entrypoint, keep same-session loading path-based and do not replace it with Skill(tdd-guide) unless that skill name is explicitly host-visible in the current session."
          ],
          "locked_for_execution": true,
          "lock_source": "current_skill_routing_selected",
          "reconciliation_state": "current_surfaced",
          "requires_resolution": true
        }
      ],
      "post_execution": [
        {
          "skill_id": "scholarly-publishing",
          "phase_id": null,
          "reason": "internal specialist recommender selected a bounded specialist candidate for governed execution",
          "task_slice": "internal specialist recommender selected a bounded specialist candidate for governed execution",
          "native_skill_entrypoint": "C:\\Users\\Administrator\\.codeium\\windsurf-next\\skills\\vibe\\bundled\\skills\\scholarly-publishing\\SKILL.runtime-mirror.md",
          "skill_md_path": "C:\\Users\\Administrator\\.codeium\\windsurf-next\\skills\\vibe\\bundled\\skills\\scholarly-publishing\\SKILL.runtime-mirror.md",
          "dispatch_phase": "post_execution",
          "parallelizable_in_root_xl": true,
          "native_usage_required": true,
          "usage_required": true,
          "skill_root": "C:\\Users\\Administrator\\.codeium\\windsurf-next\\skills\\vibe\\bundled\\skills\\scholarly-publishing",
          "bounded_role": "specialist_assist",
          "must_preserve_workflow": true,
          "binding_profile": "deliverable",
          "lane_policy": "bounded_parallel",
          "write_scope": "specialist:deliverable:scholarly-publishing",
          "review_mode": "checkpoint_after_step",
          "execution_priority": 70,
          "required_inputs": [
            "bounded specialist subtask contract",
            "frozen requirement context",
            "relevant source files or domain artifacts"
          ],
          "expected_outputs": [
            "bounded specialist findings or code changes",
            "verification notes aligned with the specialist skill"
          ],
          "verification_expectation": "Preserve the specialist skill's native workflow, boundaries, and validation style.",
          "progressive_load_policy": [
            "Open the specialist C:\\Users\\Administrator\\.codeium\\windsurf-next\\skills\\vibe\\bundled\\skills\\scholarly-publishing\\SKILL.runtime-mirror.md entrypoint first.",
            "If this specialist is disclosed only by native_skill_entrypoint, keep same-session loading path-based and do not replace it with Skill(scholarly-publishing) unless that skill name is explicitly host-visible in the current session."
          ],
          "locked_for_execution": true,
          "lock_source": "previous_skill_execution_lock",
          "reconciliation_state": "inherited_not_currently_surfaced",
          "requires_resolution": true
        }
      ],
      "verification": []
    },
    "dispatch_resolution": {
      "source": "plan_execute_selected_skill_execution",
      "frozen_selected_skill_execution_count": 3,
      "selected_skill_execution_count": 3,
      "auto_selected_skill_execution_count": 0,
      "same_round_auto_absorb_applied": false,
      "skill_execution_resolution_path": null
    },
    "two_stage_review": {
      "enabled": false,
      "review_receipt_count": 0,
      "review_receipt_paths": []
    }
  },
  "plan_shadow": {
    "path": "E:\\Code\\repo\\ai-teaching-assistant-frontend\\outputs\\runtime\\vibe-sessions\\20260507T104805Z-2fa851d5\\plan-derived-execution-shadow.json",
    "candidate_unit_count": 17,
    "executable_unit_count": 1,
    "skill_execution_unit_count": 7,
    "advisory_only_unit_count": 6,
    "ambiguous_unit_count": 3
  },
  "specialist_accounting": {
    "recommendation_count": 2,
    "matched_skill_ids": [
      "verification-before-completion",
      "tdd-guide"
    ],
    "surfaced_skill_ids": [
      "verification-before-completion",
      "tdd-guide"
    ],
    "specialist_skill_count": 3,
    "specialist_skills": [
      "verification-before-completion",
      "tdd-guide",
      "scholarly-publishing"
    ],
    "native_usage_required": true,
    "execution_mode": "native_bounded_units",
    "effective_execution_status": "direct_current_session_routed",
    "skill_execution_unit_count": 3,
    "recommendations": [
      {
        "skill_id": "verification-before-completion",
        "skill_md_path": "C:\\Users\\Administrator\\.codeium\\windsurf-next\\skills\\vibe\\bundled\\skills\\verification-before-completion\\SKILL.runtime-mirror.md",
        "reason": "overlay recommendation from 'retrieval_advice'",
        "task_slice": "overlay recommendation from 'retrieval_advice'",
        "state": "selected",
        "dispatch_phase": "in_execution",
        "parallelizable_in_root_xl": true,
        "native_usage_required": true,
        "native_skill_entrypoint": "C:\\Users\\Administrator\\.codeium\\windsurf-next\\skills\\vibe\\bundled\\skills\\verification-before-completion\\SKILL.runtime-mirror.md",
        "skill_root": "C:\\Users\\Administrator\\.codeium\\windsurf-next\\skills\\vibe\\bundled\\skills\\verification-before-completion",
        "bounded_role": "specialist_assist",
        "must_preserve_workflow": true,
        "binding_profile": "default",
        "lane_policy": "inherit_grade",
        "write_scope": "specialist:verification-before-completion",
        "review_mode": "native_contract",
        "execution_priority": 50,
        "required_inputs": [
          "bounded specialist subtask contract",
          "frozen requirement context",
          "relevant source files or domain artifacts"
        ],
        "expected_outputs": [
          "bounded specialist findings or code changes",
          "verification notes aligned with the specialist skill"
        ],
        "verification_expectation": "Preserve the specialist skill's native workflow, boundaries, and validation style.",
        "progressive_load_policy": [
          "Open the specialist C:\\Users\\Administrator\\.codeium\\windsurf-next\\skills\\vibe\\bundled\\skills\\verification-before-completion\\SKILL.runtime-mirror.md entrypoint first.",
          "If this specialist is disclosed only by native_skill_entrypoint, keep same-session loading path-based and do not replace it with Skill(verification-before-completion) unless that skill name is explicitly host-visible in the current session."
        ],
        "legacy_source": "overlay:retrieval_advice"
      },
      {
        "skill_id": "tdd-guide",
        "skill_md_path": "C:\\Users\\Administrator\\.codeium\\windsurf-next\\skills\\vibe\\bundled\\skills\\tdd-guide\\SKILL.runtime-mirror.md",
        "reason": "internal specialist recommender selected a bounded specialist candidate for governed execution",
        "task_slice": "internal specialist recommender selected a bounded specialist candidate for governed execution",
        "state": "selected",
        "dispatch_phase": "in_execution",
        "parallelizable_in_root_xl": true,
        "native_usage_required": true,
        "native_skill_entrypoint": "C:\\Users\\Administrator\\.codeium\\windsurf-next\\skills\\vibe\\bundled\\skills\\tdd-guide\\SKILL.runtime-mirror.md",
        "skill_root": "C:\\Users\\Administrator\\.codeium\\windsurf-next\\skills\\vibe\\bundled\\skills\\tdd-guide",
        "bounded_role": "specialist_assist",
        "must_preserve_workflow": true,
        "binding_profile": "default",
        "lane_policy": "inherit_grade",
        "write_scope": "specialist:tdd-guide",
        "review_mode": "native_contract",
        "execution_priority": 50,
        "required_inputs": [
          "bounded specialist subtask contract",
          "frozen requirement context",
          "relevant source files or domain artifacts"
        ],
        "expected_outputs": [
          "bounded specialist findings or code changes",
          "verification notes aligned with the specialist skill"
        ],
        "verification_expectation": "Preserve the specialist skill's native workflow, boundaries, and validation style.",
        "progressive_load_policy": [
          "Open the specialist C:\\Users\\Administrator\\.codeium\\windsurf-next\\skills\\vibe\\bundled\\skills\\tdd-guide\\SKILL.runtime-mirror.md entrypoint first.",
          "If this specialist is disclosed only by native_skill_entrypoint, keep same-session loading path-based and do not replace it with Skill(tdd-guide) unless that skill name is explicitly host-visible in the current session."
        ],
        "legacy_source": "route_selected"
      }
    ],
    "selected_skill_execution_count": 3,
    "selected_skill_execution": [
      {
        "skill_id": "verification-before-completion",
        "phase_id": null,
        "reason": "overlay recommendation from 'retrieval_advice'",
        "task_slice": "overlay recommendation from 'retrieval_advice'",
        "native_skill_entrypoint": "C:\\Users\\Administrator\\.codeium\\windsurf-next\\skills\\vibe\\bundled\\skills\\verification-before-completion\\SKILL.runtime-mirror.md",
        "skill_md_path": "C:\\Users\\Administrator\\.codeium\\windsurf-next\\skills\\vibe\\bundled\\skills\\verification-before-completion\\SKILL.runtime-mirror.md",
        "dispatch_phase": "in_execution",
        "parallelizable_in_root_xl": true,
        "native_usage_required": true,
        "usage_required": true,
        "skill_root": "C:\\Users\\Administrator\\.codeium\\windsurf-next\\skills\\vibe\\bundled\\skills\\verification-before-completion",
        "bounded_role": "specialist_assist",
        "must_preserve_workflow": true,
        "binding_profile": "default",
        "lane_policy": "inherit_grade",
        "write_scope": "specialist:verification-before-completion",
        "review_mode": "native_contract",
        "execution_priority": 50,
        "required_inputs": [
          "bounded specialist subtask contract",
          "frozen requirement context",
          "relevant source files or domain artifacts"
        ],
        "expected_outputs": [
          "bounded specialist findings or code changes",
          "verification notes aligned with the specialist skill"
        ],
        "verification_expectation": "Preserve the specialist skill's native workflow, boundaries, and validation style.",
        "progressive_load_policy": [
          "Open the specialist C:\\Users\\Administrator\\.codeium\\windsurf-next\\skills\\vibe\\bundled\\skills\\verification-before-completion\\SKILL.runtime-mirror.md entrypoint first.",
          "If this specialist is disclosed only by native_skill_entrypoint, keep same-session loading path-based and do not replace it with Skill(verification-before-completion) unless that skill name is explicitly host-visible in the current session."
        ],
        "locked_for_execution": true,
        "lock_source": "current_skill_routing_selected",
        "reconciliation_state": "current_surfaced",
        "requires_resolution": true
      },
      {
        "skill_id": "tdd-guide",
        "phase_id": null,
        "reason": "internal specialist recommender selected a bounded specialist candidate for governed execution",
        "task_slice": "internal specialist recommender selected a bounded specialist candidate for governed execution",
        "native_skill_entrypoint": "C:\\Users\\Administrator\\.codeium\\windsurf-next\\skills\\vibe\\bundled\\skills\\tdd-guide\\SKILL.runtime-mirror.md",
        "skill_md_path": "C:\\Users\\Administrator\\.codeium\\windsurf-next\\skills\\vibe\\bundled\\skills\\tdd-guide\\SKILL.runtime-mirror.md",
        "dispatch_phase": "in_execution",
        "parallelizable_in_root_xl": true,
        "native_usage_required": true,
        "usage_required": true,
        "skill_root": "C:\\Users\\Administrator\\.codeium\\windsurf-next\\skills\\vibe\\bundled\\skills\\tdd-guide",
        "bounded_role": "specialist_assist",
        "must_preserve_workflow": true,
        "binding_profile": "default",
        "lane_policy": "inherit_grade",
        "write_scope": "specialist:tdd-guide",
        "review_mode": "native_contract",
        "execution_priority": 50,
        "required_inputs": [
          "bounded specialist subtask contract",
          "frozen requirement context",
          "relevant source files or domain artifacts"
        ],
        "expected_outputs": [
          "bounded specialist findings or code changes",
          "verification notes aligned with the specialist skill"
        ],
        "verification_expectation": "Preserve the specialist skill's native workflow, boundaries, and validation style.",
        "progressive_load_policy": [
          "Open the specialist C:\\Users\\Administrator\\.codeium\\windsurf-next\\skills\\vibe\\bundled\\skills\\tdd-guide\\SKILL.runtime-mirror.md entrypoint first.",
          "If this specialist is disclosed only by native_skill_entrypoint, keep same-session loading path-based and do not replace it with Skill(tdd-guide) unless that skill name is explicitly host-visible in the current session."
        ],
        "locked_for_execution": true,
        "lock_source": "current_skill_routing_selected",
        "reconciliation_state": "current_surfaced",
        "requires_resolution": true
      },
      {
        "skill_id": "scholarly-publishing",
        "phase_id": null,
        "reason": "internal specialist recommender selected a bounded specialist candidate for governed execution",
        "task_slice": "internal specialist recommender selected a bounded specialist candidate for governed execution",
        "native_skill_entrypoint": "C:\\Users\\Administrator\\.codeium\\windsurf-next\\skills\\vibe\\bundled\\skills\\scholarly-publishing\\SKILL.runtime-mirror.md",
        "skill_md_path": "C:\\Users\\Administrator\\.codeium\\windsurf-next\\skills\\vibe\\bundled\\skills\\scholarly-publishing\\SKILL.runtime-mirror.md",
        "dispatch_phase": "post_execution",
        "parallelizable_in_root_xl": true,
        "native_usage_required": true,
        "usage_required": true,
        "skill_root": "C:\\Users\\Administrator\\.codeium\\windsurf-next\\skills\\vibe\\bundled\\skills\\scholarly-publishing",
        "bounded_role": "specialist_assist",
        "must_preserve_workflow": true,
        "binding_profile": "deliverable",
        "lane_policy": "bounded_parallel",
        "write_scope": "specialist:deliverable:scholarly-publishing",
        "review_mode": "checkpoint_after_step",
        "execution_priority": 70,
        "required_inputs": [
          "bounded specialist subtask contract",
          "frozen requirement context",
          "relevant source files or domain artifacts"
        ],
        "expected_outputs": [
          "bounded specialist findings or code changes",
          "verification notes aligned with the specialist skill"
        ],
        "verification_expectation": "Preserve the specialist skill's native workflow, boundaries, and validation style.",
        "progressive_load_policy": [
          "Open the specialist C:\\Users\\Administrator\\.codeium\\windsurf-next\\skills\\vibe\\bundled\\skills\\scholarly-publishing\\SKILL.runtime-mirror.md entrypoint first.",
          "If this specialist is disclosed only by native_skill_entrypoint, keep same-session loading path-based and do not replace it with Skill(scholarly-publishing) unless that skill name is explicitly host-visible in the current session."
        ],
        "locked_for_execution": true,
        "lock_source": "previous_skill_execution_lock",
        "reconciliation_state": "inherited_not_currently_surfaced",
        "requires_resolution": true
      }
    ],
    "frozen_selected_skill_execution_count": 3,
    "frozen_selected_skill_execution": [
      {
        "skill_id": "verification-before-completion",
        "phase_id": null,
        "reason": "overlay recommendation from 'retrieval_advice'",
        "task_slice": "overlay recommendation from 'retrieval_advice'",
        "native_skill_entrypoint": "C:\\Users\\Administrator\\.codeium\\windsurf-next\\skills\\vibe\\bundled\\skills\\verification-before-completion\\SKILL.runtime-mirror.md",
        "skill_md_path": "C:\\Users\\Administrator\\.codeium\\windsurf-next\\skills\\vibe\\bundled\\skills\\verification-before-completion\\SKILL.runtime-mirror.md",
        "dispatch_phase": "in_execution",
        "parallelizable_in_root_xl": true,
        "native_usage_required": true,
        "usage_required": true,
        "skill_root": "C:\\Users\\Administrator\\.codeium\\windsurf-next\\skills\\vibe\\bundled\\skills\\verification-before-completion",
        "bounded_role": "specialist_assist",
        "must_preserve_workflow": true,
        "binding_profile": "default",
        "lane_policy": "inherit_grade",
        "write_scope": "specialist:verification-before-completion",
        "review_mode": "native_contract",
        "execution_priority": 50,
        "required_inputs": [
          "bounded specialist subtask contract",
          "frozen requirement context",
          "relevant source files or domain artifacts"
        ],
        "expected_outputs": [
          "bounded specialist findings or code changes",
          "verification notes aligned with the specialist skill"
        ],
        "verification_expectation": "Preserve the specialist skill's native workflow, boundaries, and validation style.",
        "progressive_load_policy": [
          "Open the specialist C:\\Users\\Administrator\\.codeium\\windsurf-next\\skills\\vibe\\bundled\\skills\\verification-before-completion\\SKILL.runtime-mirror.md entrypoint first.",
          "If this specialist is disclosed only by native_skill_entrypoint, keep same-session loading path-based and do not replace it with Skill(verification-before-completion) unless that skill name is explicitly host-visible in the current session."
        ],
        "locked_for_execution": true,
        "lock_source": "current_skill_routing_selected",
        "reconciliation_state": "current_surfaced",
        "requires_resolution": true
      },
      {
        "skill_id": "tdd-guide",
        "phase_id": null,
        "reason": "internal specialist recommender selected a bounded specialist candidate for governed execution",
        "task_slice": "internal specialist recommender selected a bounded specialist candidate for governed execution",
        "native_skill_entrypoint": "C:\\Users\\Administrator\\.codeium\\windsurf-next\\skills\\vibe\\bundled\\skills\\tdd-guide\\SKILL.runtime-mirror.md",
        "skill_md_path": "C:\\Users\\Administrator\\.codeium\\windsurf-next\\skills\\vibe\\bundled\\skills\\tdd-guide\\SKILL.runtime-mirror.md",
        "dispatch_phase": "in_execution",
        "parallelizable_in_root_xl": true,
        "native_usage_required": true,
        "usage_required": true,
        "skill_root": "C:\\Users\\Administrator\\.codeium\\windsurf-next\\skills\\vibe\\bundled\\skills\\tdd-guide",
        "bounded_role": "specialist_assist",
        "must_preserve_workflow": true,
        "binding_profile": "default",
        "lane_policy": "inherit_grade",
        "write_scope": "specialist:tdd-guide",
        "review_mode": "native_contract",
        "execution_priority": 50,
        "required_inputs": [
          "bounded specialist subtask contract",
          "frozen requirement context",
          "relevant source files or domain artifacts"
        ],
        "expected_outputs": [
          "bounded specialist findings or code changes",
          "verification notes aligned with the specialist skill"
        ],
        "verification_expectation": "Preserve the specialist skill's native workflow, boundaries, and validation style.",
        "progressive_load_policy": [
          "Open the specialist C:\\Users\\Administrator\\.codeium\\windsurf-next\\skills\\vibe\\bundled\\skills\\tdd-guide\\SKILL.runtime-mirror.md entrypoint first.",
          "If this specialist is disclosed only by native_skill_entrypoint, keep same-session loading path-based and do not replace it with Skill(tdd-guide) unless that skill name is explicitly host-visible in the current session."
        ],
        "locked_for_execution": true,
        "lock_source": "current_skill_routing_selected",
        "reconciliation_state": "current_surfaced",
        "requires_resolution": true
      },
      {
        "skill_id": "scholarly-publishing",
        "phase_id": null,
        "reason": "internal specialist recommender selected a bounded specialist candidate for governed execution",
        "task_slice": "internal specialist recommender selected a bounded specialist candidate for governed execution",
        "native_skill_entrypoint": "C:\\Users\\Administrator\\.codeium\\windsurf-next\\skills\\vibe\\bundled\\skills\\scholarly-publishing\\SKILL.runtime-mirror.md",
        "skill_md_path": "C:\\Users\\Administrator\\.codeium\\windsurf-next\\skills\\vibe\\bundled\\skills\\scholarly-publishing\\SKILL.runtime-mirror.md",
        "dispatch_phase": "post_execution",
        "parallelizable_in_root_xl": true,
        "native_usage_required": true,
        "usage_required": true,
        "skill_root": "C:\\Users\\Administrator\\.codeium\\windsurf-next\\skills\\vibe\\bundled\\skills\\scholarly-publishing",
        "bounded_role": "specialist_assist",
        "must_preserve_workflow": true,
        "binding_profile": "deliverable",
        "lane_policy": "bounded_parallel",
        "write_scope": "specialist:deliverable:scholarly-publishing",
        "review_mode": "checkpoint_after_step",
        "execution_priority": 70,
        "required_inputs": [
          "bounded specialist subtask contract",
          "frozen requirement context",
          "relevant source files or domain artifacts"
        ],
        "expected_outputs": [
          "bounded specialist findings or code changes",
          "verification notes aligned with the specialist skill"
        ],
        "verification_expectation": "Preserve the specialist skill's native workflow, boundaries, and validation style.",
        "progressive_load_policy": [
          "Open the specialist C:\\Users\\Administrator\\.codeium\\windsurf-next\\skills\\vibe\\bundled\\skills\\scholarly-publishing\\SKILL.runtime-mirror.md entrypoint first.",
          "If this specialist is disclosed only by native_skill_entrypoint, keep same-session loading path-based and do not replace it with Skill(scholarly-publishing) unless that skill name is explicitly host-visible in the current session."
        ],
        "locked_for_execution": true,
        "lock_source": "previous_skill_execution_lock",
        "reconciliation_state": "inherited_not_currently_surfaced",
        "requires_resolution": true
      }
    ],
    "auto_selected_skill_execution_count": 0,
    "auto_selected_skill_execution": [],
    "skill_execution_lock": {
      "schema_version": "v1",
      "state": "active",
      "source": "approved_plan_reentry",
      "source_run_id": "20260507T104720Z-3bcacd5f",
      "locked_skill_ids": [
        "verification-before-completion",
        "tdd-guide",
        "scholarly-publishing"
      ],
      "locked_dispatch": [
        {
          "skill_id": "verification-before-completion",
          "skill_md_path": "C:\\Users\\Administrator\\.codeium\\windsurf-next\\skills\\vibe\\bundled\\skills\\verification-before-completion\\SKILL.runtime-mirror.md",
          "reason": "overlay recommendation from 'retrieval_advice'",
          "task_slice": "overlay recommendation from 'retrieval_advice'",
          "state": "selected",
          "dispatch_phase": "in_execution",
          "parallelizable_in_root_xl": true,
          "native_usage_required": true,
          "native_skill_entrypoint": "C:\\Users\\Administrator\\.codeium\\windsurf-next\\skills\\vibe\\bundled\\skills\\verification-before-completion\\SKILL.runtime-mirror.md",
          "skill_root": "C:\\Users\\Administrator\\.codeium\\windsurf-next\\skills\\vibe\\bundled\\skills\\verification-before-completion",
          "bounded_role": "specialist_assist",
          "must_preserve_workflow": true,
          "binding_profile": "default",
          "lane_policy": "inherit_grade",
          "write_scope": "specialist:verification-before-completion",
          "review_mode": "native_contract",
          "execution_priority": 50,
          "required_inputs": [
            "bounded specialist subtask contract",
            "frozen requirement context",
            "relevant source files or domain artifacts"
          ],
          "expected_outputs": [
            "bounded specialist findings or code changes",
            "verification notes aligned with the specialist skill"
          ],
          "verification_expectation": "Preserve the specialist skill's native workflow, boundaries, and validation style.",
          "progressive_load_policy": [
            "Open the specialist C:\\Users\\Administrator\\.codeium\\windsurf-next\\skills\\vibe\\bundled\\skills\\verification-before-completion\\SKILL.runtime-mirror.md entrypoint first.",
            "If this specialist is disclosed only by native_skill_entrypoint, keep same-session loading path-based and do not replace it with Skill(verification-before-completion) unless that skill name is explicitly host-visible in the current session."
          ],
          "legacy_source": "overlay:retrieval_advice",
          "locked_for_execution": true,
          "lock_source": "current_skill_routing_selected",
          "reconciliation_state": "current_surfaced",
          "requires_resolution": true
        },
        {
          "skill_id": "tdd-guide",
          "skill_md_path": "C:\\Users\\Administrator\\.codeium\\windsurf-next\\skills\\vibe\\bundled\\skills\\tdd-guide\\SKILL.runtime-mirror.md",
          "reason": "internal specialist recommender selected a bounded specialist candidate for governed execution",
          "task_slice": "internal specialist recommender selected a bounded specialist candidate for governed execution",
          "state": "selected",
          "dispatch_phase": "in_execution",
          "parallelizable_in_root_xl": true,
          "native_usage_required": true,
          "native_skill_entrypoint": "C:\\Users\\Administrator\\.codeium\\windsurf-next\\skills\\vibe\\bundled\\skills\\tdd-guide\\SKILL.runtime-mirror.md",
          "skill_root": "C:\\Users\\Administrator\\.codeium\\windsurf-next\\skills\\vibe\\bundled\\skills\\tdd-guide",
          "bounded_role": "specialist_assist",
          "must_preserve_workflow": true,
          "binding_profile": "default",
          "lane_policy": "inherit_grade",
          "write_scope": "specialist:tdd-guide",
          "review_mode": "native_contract",
          "execution_priority": 50,
          "required_inputs": [
            "bounded specialist subtask contract",
            "frozen requirement context",
            "relevant source files or domain artifacts"
          ],
          "expected_outputs": [
            "bounded specialist findings or code changes",
            "verification notes aligned with the specialist skill"
          ],
          "verification_expectation": "Preserve the specialist skill's native workflow, boundaries, and validation style.",
          "progressive_load_policy": [
            "Open the specialist C:\\Users\\Administrator\\.codeium\\windsurf-next\\skills\\vibe\\bundled\\skills\\tdd-guide\\SKILL.runtime-mirror.md entrypoint first.",
            "If this specialist is disclosed only by native_skill_entrypoint, keep same-session loading path-based and do not replace it with Skill(tdd-guide) unless that skill name is explicitly host-visible in the current session."
          ],
          "legacy_source": "route_selected",
          "locked_for_execution": true,
          "lock_source": "current_skill_routing_selected",
          "reconciliation_state": "current_surfaced",
          "requires_resolution": true
        },
        {
          "skill_id": "scholarly-publishing",
          "skill_md_path": "C:\\Users\\Administrator\\.codeium\\windsurf-next\\skills\\vibe\\bundled\\skills\\scholarly-publishing\\SKILL.runtime-mirror.md",
          "reason": "internal specialist recommender selected a bounded specialist candidate for governed execution",
          "task_slice": "internal specialist recommender selected a bounded specialist candidate for governed execution",
          "state": "selected",
          "dispatch_phase": "post_execution",
          "parallelizable_in_root_xl": true,
          "native_usage_required": true,
          "native_skill_entrypoint": "C:\\Users\\Administrator\\.codeium\\windsurf-next\\skills\\vibe\\bundled\\skills\\scholarly-publishing\\SKILL.runtime-mirror.md",
          "skill_root": "C:\\Users\\Administrator\\.codeium\\windsurf-next\\skills\\vibe\\bundled\\skills\\scholarly-publishing",
          "bounded_role": "specialist_assist",
          "must_preserve_workflow": true,
          "binding_profile": "deliverable",
          "lane_policy": "bounded_parallel",
          "write_scope": "specialist:deliverable:scholarly-publishing",
          "review_mode": "checkpoint_after_step",
          "execution_priority": 70,
          "required_inputs": [
            "bounded specialist subtask contract",
            "frozen requirement context",
            "relevant source files or domain artifacts"
          ],
          "expected_outputs": [
            "bounded specialist findings or code changes",
            "verification notes aligned with the specialist skill"
          ],
          "verification_expectation": "Preserve the specialist skill's native workflow, boundaries, and validation style.",
          "progressive_load_policy": [
            "Open the specialist C:\\Users\\Administrator\\.codeium\\windsurf-next\\skills\\vibe\\bundled\\skills\\scholarly-publishing\\SKILL.runtime-mirror.md entrypoint first.",
            "If this specialist is disclosed only by native_skill_entrypoint, keep same-session loading path-based and do not replace it with Skill(scholarly-publishing) unless that skill name is explicitly host-visible in the current session."
          ],
          "legacy_source": "route_selected",
          "locked_for_execution": true,
          "lock_source": "previous_skill_execution_lock",
          "reconciliation_state": "inherited_not_currently_surfaced",
          "requires_resolution": true
        }
      ],
      "resolution_required": true,
      "resolution_states": [
        "executed",
        "not_applicable",
        "deferred",
        "failed"
      ]
    },
    "skill_execution_lock_active": true,
    "skill_execution_lock_summary": {
      "active": true,
      "locked_skill_count": 3,
      "locked_skill_ids": [
        "verification-before-completion",
        "tdd-guide",
        "scholarly-publishing"
      ],
      "source": "approved_plan_reentry",
      "source_run_id": "20260507T104720Z-3bcacd5f",
      "resolution_required": true
    },
    "specialist_lock_resolution": {
      "active": true,
      "locked_skill_ids": [
        "verification-before-completion",
        "tdd-guide",
        "scholarly-publishing"
      ],
      "executed_skill_ids": [
        "tdd-guide",
        "verification-before-completion",
        "scholarly-publishing"
      ],
      "not_applicable_skill_ids": [],
      "deferred_skill_ids": [],
      "failed_skill_ids": [],
      "unresolved_skill_ids": [],
      "delivery_blocking": false
    },
    "requested_host_adapter_id": "windsurf",
    "effective_host_adapter_id": "windsurf",
    "phase_binding_counts": {
      "pre_execution": 0,
      "in_execution": 2,
      "post_execution": 1,
      "verification": 0
    },
    "parallelizable_skill_execution_count": 3,
    "attempted_specialist_unit_count": 0,
    "executed_specialist_unit_count": 0,
    "failed_specialist_unit_count": 0,
    "direct_routed_skill_execution_unit_count": 3,
    "direct_routed_skill_execution_units": [
      {
        "unit_id": "specialist-in_execution-ungrouped-tdd-guide-specialist",
        "skill_id": "tdd-guide",
        "dispatch_phase": "in_execution",
        "binding_profile": "default",
        "lane_policy": "inherit_grade",
        "parallelizable": true,
        "result_path": "E:\\Code\\repo\\ai-teaching-assistant-frontend\\outputs\\runtime\\vibe-sessions\\20260507T104805Z-2fa851d5\\child-lanes\\specialist-in_execution-ungrouped-tdd-guide\\execution-results\\specialist-in_execution-ungrouped-tdd-guide-specialist.json",
        "verification_passed": true,
        "execution_driver": "direct_current_session_route",
        "live_native_execution": false,
        "degraded": false,
        "lane_receipt_path": "E:\\Code\\repo\\ai-teaching-assistant-frontend\\outputs\\runtime\\vibe-sessions\\20260507T104805Z-2fa851d5\\child-lanes\\specialist-in_execution-ungrouped-tdd-guide\\lane-receipt.json"
      },
      {
        "unit_id": "specialist-in_execution-ungrouped-verification-before-completion-specialist",
        "skill_id": "verification-before-completion",
        "dispatch_phase": "in_execution",
        "binding_profile": "default",
        "lane_policy": "inherit_grade",
        "parallelizable": true,
        "result_path": "E:\\Code\\repo\\ai-teaching-assistant-frontend\\outputs\\runtime\\vibe-sessions\\20260507T104805Z-2fa851d5\\child-lanes\\specialist-in_execution-ungrouped-verification-before-completion\\execution-results\\specialist-in_execution-ungrouped-verification-before-completion-specialist.json",
        "verification_passed": true,
        "execution_driver": "direct_current_session_route",
        "live_native_execution": false,
        "degraded": false,
        "lane_receipt_path": "E:\\Code\\repo\\ai-teaching-assistant-frontend\\outputs\\runtime\\vibe-sessions\\20260507T104805Z-2fa851d5\\child-lanes\\specialist-in_execution-ungrouped-verification-before-completion\\lane-receipt.json"
      },
      {
        "unit_id": "specialist-post_execution-ungrouped-scholarly-publishing-specialist",
        "skill_id": "scholarly-publishing",
        "dispatch_phase": "post_execution",
        "binding_profile": "deliverable",
        "lane_policy": "bounded_parallel",
        "parallelizable": true,
        "result_path": "E:\\Code\\repo\\ai-teaching-assistant-frontend\\outputs\\runtime\\vibe-sessions\\20260507T104805Z-2fa851d5\\child-lanes\\specialist-post_execution-ungrouped-scholarly-publishing\\execution-results\\specialist-post_execution-ungrouped-scholarly-publishing-specialist.json",
        "verification_passed": true,
        "execution_driver": "direct_current_session_route",
        "live_native_execution": false,
        "degraded": false,
        "lane_receipt_path": "E:\\Code\\repo\\ai-teaching-assistant-frontend\\outputs\\runtime\\vibe-sessions\\20260507T104805Z-2fa851d5\\child-lanes\\specialist-post_execution-ungrouped-scholarly-publishing\\lane-receipt.json"
      }
    ],
    "executed_skill_execution_units": [],
    "failed_skill_execution_units": [],
    "blocked_skill_execution_unit_count": 0,
    "blocked_skill_execution_units": [],
    "degraded_skill_execution_unit_count": 0,
    "degraded_skill_execution_units": [],
    "blocked_skill_ids": [],
    "degraded_skill_ids": [],
    "ghost_match_skill_ids": [],
    "execution_skill_outcome_count": 3,
    "execution_skill_outcomes": [
      {
        "unit_id": "specialist-in_execution-ungrouped-tdd-guide-specialist",
        "skill_id": "tdd-guide",
        "dispatch_phase": "in_execution",
        "binding_profile": "default",
        "lane_policy": "inherit_grade",
        "parallelizable": true,
        "result_path": "E:\\Code\\repo\\ai-teaching-assistant-frontend\\outputs\\runtime\\vibe-sessions\\20260507T104805Z-2fa851d5\\child-lanes\\specialist-in_execution-ungrouped-tdd-guide\\execution-results\\specialist-in_execution-ungrouped-tdd-guide-specialist.json",
        "verification_passed": true,
        "execution_driver": "direct_current_session_route",
        "live_native_execution": false,
        "degraded": false,
        "lane_receipt_path": "E:\\Code\\repo\\ai-teaching-assistant-frontend\\outputs\\runtime\\vibe-sessions\\20260507T104805Z-2fa851d5\\child-lanes\\specialist-in_execution-ungrouped-tdd-guide\\lane-receipt.json"
      },
      {
        "unit_id": "specialist-in_execution-ungrouped-verification-before-completion-specialist",
        "skill_id": "verification-before-completion",
        "dispatch_phase": "in_execution",
        "binding_profile": "default",
        "lane_policy": "inherit_grade",
        "parallelizable": true,
        "result_path": "E:\\Code\\repo\\ai-teaching-assistant-frontend\\outputs\\runtime\\vibe-sessions\\20260507T104805Z-2fa851d5\\child-lanes\\specialist-in_execution-ungrouped-verification-before-completion\\execution-results\\specialist-in_execution-ungrouped-verification-before-completion-specialist.json",
        "verification_passed": true,
        "execution_driver": "direct_current_session_route",
        "live_native_execution": false,
        "degraded": false,
        "lane_receipt_path": "E:\\Code\\repo\\ai-teaching-assistant-frontend\\outputs\\runtime\\vibe-sessions\\20260507T104805Z-2fa851d5\\child-lanes\\specialist-in_execution-ungrouped-verification-before-completion\\lane-receipt.json"
      },
      {
        "unit_id": "specialist-post_execution-ungrouped-scholarly-publishing-specialist",
        "skill_id": "scholarly-publishing",
        "dispatch_phase": "post_execution",
        "binding_profile": "deliverable",
        "lane_policy": "bounded_parallel",
        "parallelizable": true,
        "result_path": "E:\\Code\\repo\\ai-teaching-assistant-frontend\\outputs\\runtime\\vibe-sessions\\20260507T104805Z-2fa851d5\\child-lanes\\specialist-post_execution-ungrouped-scholarly-publishing\\execution-results\\specialist-post_execution-ungrouped-scholarly-publishing-specialist.json",
        "verification_passed": true,
        "execution_driver": "direct_current_session_route",
        "live_native_execution": false,
        "degraded": false,
        "lane_receipt_path": "E:\\Code\\repo\\ai-teaching-assistant-frontend\\outputs\\runtime\\vibe-sessions\\20260507T104805Z-2fa851d5\\child-lanes\\specialist-post_execution-ungrouped-scholarly-publishing\\lane-receipt.json"
      }
    ],
    "skill_execution_resolution_path": null,
    "promotion_funnel": {
      "matched": 2,
      "surfaced": 2,
      "dispatched": 3,
      "executed": 0,
      "routed": 3,
      "blocked_due_to_destructive": 0,
      "degraded_due_to_missing_contract": 0,
      "ghost_match": 0,
      "executed_per_matched": 0.0,
      "executed_rate": 0.0
    },
    "original_local_suggestion_count": 0,
    "original_local_specialist_suggestions": [],
    "local_suggestion_count": 0,
    "local_specialist_suggestions": [],
    "auto_absorb_gate": {
      "enabled": false,
      "receipt_path": null,
      "reason": "skill_execution_lock_is_authority"
    },
    "escalation_required": false,
    "escalation_request_path": null
  },
  "specialist_decision": {
    "decision_state": "approved_dispatch",
    "resolution_mode": "approved_dispatch",
    "recommendation_count": 2,
    "candidate_skill_ids_reviewed": [
      "verification-before-completion",
      "tdd-guide",
      "scholarly-publishing"
    ],
    "selected_skill_ids": [
      "verification-before-completion",
      "tdd-guide",
      "scholarly-publishing"
    ],
    "rejected_candidates": [],
    "matched_skill_ids": [
      "verification-before-completion",
      "tdd-guide"
    ],
    "surfaced_skill_ids": [
      "verification-before-completion",
      "tdd-guide"
    ],
    "approved_dispatch_skill_ids": [
      "verification-before-completion",
      "tdd-guide",
      "scholarly-publishing"
    ],
    "local_suggestion_skill_ids": [],
    "blocked_skill_ids": [],
    "degraded_skill_ids": [],
    "repo_asset_fallback": {
      "used": false,
      "asset_paths": [],
      "reason": "",
      "legal_basis": "",
      "traceability_basis": []
    },
    "notes": "Bounded specialist recommendations were surfaced and promoted into effective approved dispatch.",
    "source": "runtime_structural_projection",
    "override_source_path": null
  },
  "specialist_user_disclosure": {
    "enabled": true,
    "stage": "plan_execute",
    "mode": "selected_skill_execution_pre_execution_unified_once",
    "timing": "before_execution",
    "scope": "selected_skill_execution_only",
    "aggregation": "unified_once",
    "path_source": "native_skill_entrypoint",
    "routed_skill_count": 3,
    "routed_skills": [
      {
        "skill_id": "verification-before-completion",
        "native_skill_entrypoint": "C:\\Users\\Administrator\\.codeium\\windsurf-next\\skills\\vibe\\bundled\\skills\\verification-before-completion\\SKILL.runtime-mirror.md",
        "native_skill_entrypoint_raw": "C:\\Users\\Administrator\\.codeium\\windsurf-next\\skills\\vibe\\bundled\\skills\\verification-before-completion\\SKILL.runtime-mirror.md",
        "entrypoint_path_state": "resolved",
        "entrypoint_missing": false,
        "entrypoint_path_invalid": false,
        "entrypoint_requirement_satisfied": true,
        "native_skill_description": null,
        "dispatch_phase": "in_execution",
        "write_scope": "specialist:verification-before-completion",
        "review_mode": "native_contract"
      },
      {
        "skill_id": "tdd-guide",
        "native_skill_entrypoint": "C:\\Users\\Administrator\\.codeium\\windsurf-next\\skills\\vibe\\bundled\\skills\\tdd-guide\\SKILL.runtime-mirror.md",
        "native_skill_entrypoint_raw": "C:\\Users\\Administrator\\.codeium\\windsurf-next\\skills\\vibe\\bundled\\skills\\tdd-guide\\SKILL.runtime-mirror.md",
        "entrypoint_path_state": "resolved",
        "entrypoint_missing": false,
        "entrypoint_path_invalid": false,
        "entrypoint_requirement_satisfied": true,
        "native_skill_description": null,
        "dispatch_phase": "in_execution",
        "write_scope": "specialist:tdd-guide",
        "review_mode": "native_contract"
      },
      {
        "skill_id": "scholarly-publishing",
        "native_skill_entrypoint": "C:\\Users\\Administrator\\.codeium\\windsurf-next\\skills\\vibe\\bundled\\skills\\scholarly-publishing\\SKILL.runtime-mirror.md",
        "native_skill_entrypoint_raw": "C:\\Users\\Administrator\\.codeium\\windsurf-next\\skills\\vibe\\bundled\\skills\\scholarly-publishing\\SKILL.runtime-mirror.md",
        "entrypoint_path_state": "resolved",
        "entrypoint_missing": false,
        "entrypoint_path_invalid": false,
        "entrypoint_requirement_satisfied": true,
        "native_skill_description": null,
        "dispatch_phase": "post_execution",
        "write_scope": "specialist:deliverable:scholarly-publishing",
        "review_mode": "checkpoint_after_step"
      }
    ],
    "rendered_text": "Pre-execution skill disclosure:\n- verification-before-completion -> C:\\Users\\Administrator\\.codeium\\windsurf-next\\skills\\vibe\\bundled\\skills\\verification-before-completion\\SKILL.runtime-mirror.md\n- tdd-guide -> C:\\Users\\Administrator\\.codeium\\windsurf-next\\skills\\vibe\\bundled\\skills\\tdd-guide\\SKILL.runtime-mirror.md\n- scholarly-publishing -> C:\\Users\\Administrator\\.codeium\\windsurf-next\\skills\\vibe\\bundled\\skills\\scholarly-publishing\\SKILL.runtime-mirror.md"
  },
  "dispatch_integrity": {
    "recommendation_skill_ids": [
      "verification-before-completion",
      "tdd-guide"
    ],
    "recommendation_resolution_keys": [
      "in_execution|verification-before-completion",
      "in_execution|tdd-guide"
    ],
    "matched_skill_ids": [
      "verification-before-completion",
      "tdd-guide"
    ],
    "surfaced_skill_ids": [
      "verification-before-completion",
      "tdd-guide"
    ],
    "approved_dispatch_skill_ids": [
      "verification-before-completion",
      "tdd-guide",
      "scholarly-publishing"
    ],
    "approved_dispatch_resolution_keys": [
      "in_execution|verification-before-completion",
      "in_execution|tdd-guide",
      "post_execution|scholarly-publishing"
    ],
    "local_suggestion_skill_ids": [],
    "local_suggestion_resolution_keys": [],
    "blocked_skill_ids": [],
    "degraded_skill_ids": [],
    "ghost_match_skill_ids": [],
    "executed_specialist_skill_ids": [],
    "executed_specialist_resolution_keys": [],
    "direct_routed_specialist_skill_ids": [
      "tdd-guide",
      "verification-before-completion",
      "scholarly-publishing"
    ],
    "direct_routed_specialist_resolution_keys": [
      "in_execution|tdd-guide",
      "in_execution|verification-before-completion",
      "post_execution|scholarly-publishing"
    ],
    "resolved_specialist_skill_ids": [
      "tdd-guide",
      "verification-before-completion",
      "scholarly-publishing"
    ],
    "resolved_specialist_resolution_keys": [
      "in_execution|tdd-guide",
      "in_execution|verification-before-completion",
      "post_execution|scholarly-publishing"
    ],
    "approved_dispatch_subset_of_recommendations": false,
    "inherited_root_approval_allowed": false,
    "approved_dispatch_supported_by_recommendation_or_inherited_approval": false,
    "approved_dispatch_fully_executed": false,
    "approved_dispatch_fully_resolved": true,
    "executed_specialists_subset_of_approved_dispatch": true,
    "routed_specialists_subset_of_approved_dispatch": true,
    "local_suggestions_contained": true,
    "native_contract_complete_for_approved_dispatch": true,
    "matched_skills_resolved": true,
    "approved_dispatch_missing_from_recommendations": [
      "scholarly-publishing"
    ],
    "approved_dispatch_missing_from_recommendations_resolution_keys": [
      "post_execution|scholarly-publishing"
    ],
    "approved_dispatch_not_executed": [
      "in_execution|verification-before-completion",
      "in_execution|tdd-guide",
      "post_execution|scholarly-publishing"
    ],
    "approved_dispatch_not_resolved": [],
    "executed_without_approval": [],
    "routed_without_approval": [],
    "local_suggestions_executed_without_approval": [],
    "dispatch_contract_incomplete_skill_ids": [],
    "proof_passed": false
  },
  "status": "completed_with_failures",
  "waves": [
    {
      "wave_id": "wave-1",
      "description": "Execute governed runtime proof units against repo-safe local commands.",
      "status": "failed",
      "started_at": "2026-05-07T10:48:10Z",
      "finished_at": "2026-05-07T10:48:13Z",
      "planned_unit_count": 5,
      "executed_unit_count": 5,
      "steps": [
        {
          "step_id": "wave-1-parallel",
          "execution_mode": "bounded_parallel",
          "started_at": "2026-05-07T10:48:10Z",
          "finished_at": "2026-05-07T10:48:11Z",
          "planned_unit_count": 2,
          "executed_unit_count": 2,
          "status": "failed",
          "units": [
            {
              "unit_id": "runtime-neutral-freshness-gate-tests",
              "wave_id": "wave-1",
              "step_id": "wave-1-parallel",
              "lane_id": "lane-runtime-neutral-freshness-gate-tests",
              "lane_kind": "execution_unit",
              "status": "failed",
              "exit_code": 1,
              "timed_out": false,
              "verification_passed": false,
              "result_path": "E:\\Code\\repo\\ai-teaching-assistant-frontend\\outputs\\runtime\\vibe-sessions\\20260507T104805Z-2fa851d5\\child-lanes\\lane-runtime-neutral-freshness-gate-tests\\execution-results\\runtime-neutral-freshness-gate-tests.json",
              "lane_receipt_path": "E:\\Code\\repo\\ai-teaching-assistant-frontend\\outputs\\runtime\\vibe-sessions\\20260507T104805Z-2fa851d5\\child-lanes\\lane-runtime-neutral-freshness-gate-tests\\lane-receipt.json",
              "skill_id": null,
              "dispatch_phase": null,
              "binding_profile": null,
              "lane_policy": null,
              "write_scope": "tests/runtime_neutral",
              "execution_driver": null,
              "live_native_execution": false,
              "degraded": false,
              "prompt_path": null,
              "prompt_injection_complete": false,
              "missing_prompt_injection_fields": null
            },
            {
              "unit_id": "release-install-runtime-coherence-gate",
              "wave_id": "wave-1",
              "step_id": "wave-1-parallel",
              "lane_id": "lane-release-install-runtime-coherence-gate",
              "lane_kind": "execution_unit",
              "status": "completed",
              "exit_code": 0,
              "timed_out": false,
              "verification_passed": true,
              "result_path": "E:\\Code\\repo\\ai-teaching-assistant-frontend\\outputs\\runtime\\vibe-sessions\\20260507T104805Z-2fa851d5\\child-lanes\\lane-release-install-runtime-coherence-gate\\execution-results\\release-install-runtime-coherence-gate.json",
              "lane_receipt_path": "E:\\Code\\repo\\ai-teaching-assistant-frontend\\outputs\\runtime\\vibe-sessions\\20260507T104805Z-2fa851d5\\child-lanes\\lane-release-install-runtime-coherence-gate\\lane-receipt.json",
              "skill_id": null,
              "dispatch_phase": null,
              "binding_profile": null,
              "lane_policy": null,
              "write_scope": "scripts/verify",
              "execution_driver": null,
              "live_native_execution": false,
              "degraded": false,
              "prompt_path": null,
              "prompt_injection_complete": false,
              "missing_prompt_injection_fields": null
            }
          ]
        },
        {
          "step_id": "wave-1-specialist-in_execution-group-1-parallel",
          "execution_mode": "bounded_parallel",
          "started_at": "2026-05-07T10:48:11Z",
          "finished_at": "2026-05-07T10:48:12Z",
          "planned_unit_count": 2,
          "executed_unit_count": 2,
          "status": "completed",
          "units": [
            {
              "unit_id": "specialist-in_execution-ungrouped-tdd-guide-specialist",
              "wave_id": "wave-1",
              "step_id": "wave-1-specialist-in_execution-group-1-parallel",
              "lane_id": "specialist-in_execution-ungrouped-tdd-guide",
              "lane_kind": "skill_execution",
              "status": "completed",
              "exit_code": 0,
              "timed_out": false,
              "verification_passed": true,
              "result_path": "E:\\Code\\repo\\ai-teaching-assistant-frontend\\outputs\\runtime\\vibe-sessions\\20260507T104805Z-2fa851d5\\child-lanes\\specialist-in_execution-ungrouped-tdd-guide\\execution-results\\specialist-in_execution-ungrouped-tdd-guide-specialist.json",
              "lane_receipt_path": "E:\\Code\\repo\\ai-teaching-assistant-frontend\\outputs\\runtime\\vibe-sessions\\20260507T104805Z-2fa851d5\\child-lanes\\specialist-in_execution-ungrouped-tdd-guide\\lane-receipt.json",
              "skill_id": "tdd-guide",
              "dispatch_phase": "in_execution",
              "binding_profile": "default",
              "lane_policy": "inherit_grade",
              "write_scope": "specialist:tdd-guide",
              "execution_driver": "direct_current_session_route",
              "live_native_execution": false,
              "degraded": false,
              "prompt_path": null,
              "prompt_injection_complete": false,
              "missing_prompt_injection_fields": null
            },
            {
              "unit_id": "specialist-in_execution-ungrouped-verification-before-completion-specialist",
              "wave_id": "wave-1",
              "step_id": "wave-1-specialist-in_execution-group-1-parallel",
              "lane_id": "specialist-in_execution-ungrouped-verification-before-completion",
              "lane_kind": "skill_execution",
              "status": "completed",
              "exit_code": 0,
              "timed_out": false,
              "verification_passed": true,
              "result_path": "E:\\Code\\repo\\ai-teaching-assistant-frontend\\outputs\\runtime\\vibe-sessions\\20260507T104805Z-2fa851d5\\child-lanes\\specialist-in_execution-ungrouped-verification-before-completion\\execution-results\\specialist-in_execution-ungrouped-verification-before-completion-specialist.json",
              "lane_receipt_path": "E:\\Code\\repo\\ai-teaching-assistant-frontend\\outputs\\runtime\\vibe-sessions\\20260507T104805Z-2fa851d5\\child-lanes\\specialist-in_execution-ungrouped-verification-before-completion\\lane-receipt.json",
              "skill_id": "verification-before-completion",
              "dispatch_phase": "in_execution",
              "binding_profile": "default",
              "lane_policy": "inherit_grade",
              "write_scope": "specialist:verification-before-completion",
              "execution_driver": "direct_current_session_route",
              "live_native_execution": false,
              "degraded": false,
              "prompt_path": null,
              "prompt_injection_complete": false,
              "missing_prompt_injection_fields": null
            }
          ]
        },
        {
          "step_id": "wave-1-specialist-post_execution-group-1-parallel",
          "execution_mode": "bounded_parallel",
          "started_at": "2026-05-07T10:48:12Z",
          "finished_at": "2026-05-07T10:48:13Z",
          "planned_unit_count": 1,
          "executed_unit_count": 1,
          "status": "completed",
          "units": [
            {
              "unit_id": "specialist-post_execution-ungrouped-scholarly-publishing-specialist",
              "wave_id": "wave-1",
              "step_id": "wave-1-specialist-post_execution-group-1-parallel",
              "lane_id": "specialist-post_execution-ungrouped-scholarly-publishing",
              "lane_kind": "skill_execution",
              "status": "completed",
              "exit_code": 0,
              "timed_out": false,
              "verification_passed": true,
              "result_path": "E:\\Code\\repo\\ai-teaching-assistant-frontend\\outputs\\runtime\\vibe-sessions\\20260507T104805Z-2fa851d5\\child-lanes\\specialist-post_execution-ungrouped-scholarly-publishing\\execution-results\\specialist-post_execution-ungrouped-scholarly-publishing-specialist.json",
              "lane_receipt_path": "E:\\Code\\repo\\ai-teaching-assistant-frontend\\outputs\\runtime\\vibe-sessions\\20260507T104805Z-2fa851d5\\child-lanes\\specialist-post_execution-ungrouped-scholarly-publishing\\lane-receipt.json",
              "skill_id": "scholarly-publishing",
              "dispatch_phase": "post_execution",
              "binding_profile": "deliverable",
              "lane_policy": "bounded_parallel",
              "write_scope": "specialist:deliverable:scholarly-publishing",
              "execution_driver": "direct_current_session_route",
              "live_native_execution": false,
              "degraded": false,
              "prompt_path": null,
              "prompt_injection_complete": false,
              "missing_prompt_injection_fields": null
            }
          ]
        }
      ],
      "units": [
        {
          "unit_id": "runtime-neutral-freshness-gate-tests",
          "wave_id": "wave-1",
          "step_id": "wave-1-parallel",
          "lane_id": "lane-runtime-neutral-freshness-gate-tests",
          "lane_kind": "execution_unit",
          "status": "failed",
          "exit_code": 1,
          "timed_out": false,
          "verification_passed": false,
          "result_path": "E:\\Code\\repo\\ai-teaching-assistant-frontend\\outputs\\runtime\\vibe-sessions\\20260507T104805Z-2fa851d5\\child-lanes\\lane-runtime-neutral-freshness-gate-tests\\execution-results\\runtime-neutral-freshness-gate-tests.json",
          "lane_receipt_path": "E:\\Code\\repo\\ai-teaching-assistant-frontend\\outputs\\runtime\\vibe-sessions\\20260507T104805Z-2fa851d5\\child-lanes\\lane-runtime-neutral-freshness-gate-tests\\lane-receipt.json",
          "skill_id": null,
          "dispatch_phase": null,
          "binding_profile": null,
          "lane_policy": null,
          "write_scope": "tests/runtime_neutral",
          "execution_driver": null,
          "live_native_execution": false,
          "degraded": false,
          "prompt_path": null,
          "prompt_injection_complete": false,
          "missing_prompt_injection_fields": null
        },
        {
          "unit_id": "release-install-runtime-coherence-gate",
          "wave_id": "wave-1",
          "step_id": "wave-1-parallel",
          "lane_id": "lane-release-install-runtime-coherence-gate",
          "lane_kind": "execution_unit",
          "status": "completed",
          "exit_code": 0,
          "timed_out": false,
          "verification_passed": true,
          "result_path": "E:\\Code\\repo\\ai-teaching-assistant-frontend\\outputs\\runtime\\vibe-sessions\\20260507T104805Z-2fa851d5\\child-lanes\\lane-release-install-runtime-coherence-gate\\execution-results\\release-install-runtime-coherence-gate.json",
          "lane_receipt_path": "E:\\Code\\repo\\ai-teaching-assistant-frontend\\outputs\\runtime\\vibe-sessions\\20260507T104805Z-2fa851d5\\child-lanes\\lane-release-install-runtime-coherence-gate\\lane-receipt.json",
          "skill_id": null,
          "dispatch_phase": null,
          "binding_profile": null,
          "lane_policy": null,
          "write_scope": "scripts/verify",
          "execution_driver": null,
          "live_native_execution": false,
          "degraded": false,
          "prompt_path": null,
          "prompt_injection_complete": false,
          "missing_prompt_injection_fields": null
        },
        {
          "unit_id": "specialist-in_execution-ungrouped-tdd-guide-specialist",
          "wave_id": "wave-1",
          "step_id": "wave-1-specialist-in_execution-group-1-parallel",
          "lane_id": "specialist-in_execution-ungrouped-tdd-guide",
          "lane_kind": "skill_execution",
          "status": "completed",
          "exit_code": 0,
          "timed_out": false,
          "verification_passed": true,
          "result_path": "E:\\Code\\repo\\ai-teaching-assistant-frontend\\outputs\\runtime\\vibe-sessions\\20260507T104805Z-2fa851d5\\child-lanes\\specialist-in_execution-ungrouped-tdd-guide\\execution-results\\specialist-in_execution-ungrouped-tdd-guide-specialist.json",
          "lane_receipt_path": "E:\\Code\\repo\\ai-teaching-assistant-frontend\\outputs\\runtime\\vibe-sessions\\20260507T104805Z-2fa851d5\\child-lanes\\specialist-in_execution-ungrouped-tdd-guide\\lane-receipt.json",
          "skill_id": "tdd-guide",
          "dispatch_phase": "in_execution",
          "binding_profile": "default",
          "lane_policy": "inherit_grade",
          "write_scope": "specialist:tdd-guide",
          "execution_driver": "direct_current_session_route",
          "live_native_execution": false,
          "degraded": false,
          "prompt_path": null,
          "prompt_injection_complete": false,
          "missing_prompt_injection_fields": null
        },
        {
          "unit_id": "specialist-in_execution-ungrouped-verification-before-completion-specialist",
          "wave_id": "wave-1",
          "step_id": "wave-1-specialist-in_execution-group-1-parallel",
          "lane_id": "specialist-in_execution-ungrouped-verification-before-completion",
          "lane_kind": "skill_execution",
          "status": "completed",
          "exit_code": 0,
          "timed_out": false,
          "verification_passed": true,
          "result_path": "E:\\Code\\repo\\ai-teaching-assistant-frontend\\outputs\\runtime\\vibe-sessions\\20260507T104805Z-2fa851d5\\child-lanes\\specialist-in_execution-ungrouped-verification-before-completion\\execution-results\\specialist-in_execution-ungrouped-verification-before-completion-specialist.json",
          "lane_receipt_path": "E:\\Code\\repo\\ai-teaching-assistant-frontend\\outputs\\runtime\\vibe-sessions\\20260507T104805Z-2fa851d5\\child-lanes\\specialist-in_execution-ungrouped-verification-before-completion\\lane-receipt.json",
          "skill_id": "verification-before-completion",
          "dispatch_phase": "in_execution",
          "binding_profile": "default",
          "lane_policy": "inherit_grade",
          "write_scope": "specialist:verification-before-completion",
          "execution_driver": "direct_current_session_route",
          "live_native_execution": false,
          "degraded": false,
          "prompt_path": null,
          "prompt_injection_complete": false,
          "missing_prompt_injection_fields": null
        },
        {
          "unit_id": "specialist-post_execution-ungrouped-scholarly-publishing-specialist",
          "wave_id": "wave-1",
          "step_id": "wave-1-specialist-post_execution-group-1-parallel",
          "lane_id": "specialist-post_execution-ungrouped-scholarly-publishing",
          "lane_kind": "skill_execution",
          "status": "completed",
          "exit_code": 0,
          "timed_out": false,
          "verification_passed": true,
          "result_path": "E:\\Code\\repo\\ai-teaching-assistant-frontend\\outputs\\runtime\\vibe-sessions\\20260507T104805Z-2fa851d5\\child-lanes\\specialist-post_execution-ungrouped-scholarly-publishing\\execution-results\\specialist-post_execution-ungrouped-scholarly-publishing-specialist.json",
          "lane_receipt_path": "E:\\Code\\repo\\ai-teaching-assistant-frontend\\outputs\\runtime\\vibe-sessions\\20260507T104805Z-2fa851d5\\child-lanes\\specialist-post_execution-ungrouped-scholarly-publishing\\lane-receipt.json",
          "skill_id": "scholarly-publishing",
          "dispatch_phase": "post_execution",
          "binding_profile": "deliverable",
          "lane_policy": "bounded_parallel",
          "write_scope": "specialist:deliverable:scholarly-publishing",
          "execution_driver": "direct_current_session_route",
          "live_native_execution": false,
          "degraded": false,
          "prompt_path": null,
          "prompt_injection_complete": false,
          "missing_prompt_injection_fields": null
        }
      ]
    }
  ]
}